{"connect":{"statusCode":200,"response":{"id":"","name":"coincheck","private":false,"enableRateLimit":true,"countries":["JP","ID"],"rateLimit":1500,"has":{"loadMarkets":"true","cancelAllOrders":"false","cancelOrder":"true","cancelOrders":"false","CORS":"false","createDepositAddress":"false","createLimitOrder":"true","createMarketOrder":"true","createOrder":"true","deposit":"false","editOrder":"emulated","fetchBalance":"true","fetchBidsAsks":"false","fetchClosedOrders":"false","fetchCurrencies":"false","fetchDepositAddress":"false","fetchDeposits":"false","fetchFundingFees":"false","fetchL2OrderBook":"true","fetchLedger":"false","fetchMarkets":"true","fetchMyTrades":"true","fetchOHLCV":"emulated","fetchOpenOrders":"true","fetchOrder":"false","fetchOrderBook":"true","fetchOrderBooks":"false","fetchOrders":"false","fetchOrderTrades":"false","fetchStatus":"emulated","fetchTicker":"true","fetchTickers":"false","fetchTime":"false","fetchTrades":"true","fetchTradingFee":"false","fetchTradingFees":"false","fetchTradingLimits":"false","fetchTransactions":"false","fetchWithdrawals":"false","privateAPI":"true","publicAPI":"true","withdraw":"false"},"urls":{"logo":"https://user-images.githubusercontent.com/1294454/27766464-3b5c3c74-5ed9-11e7-840e-31b32968e1da.jpg","api":"https://coincheck.com/api","www":"https://coincheck.com","doc":"https://coincheck.com/documents/exchange/api","fees":["https://coincheck.com/exchange/fee","https://coincheck.com/info/fee"]}}},"markets":{"statusCode":200,"response":[{"id":"btc_jpy","symbol":"BTC/JPY","base":"BTC","quote":"JPY","limits":{"amount":{},"price":{},"cost":{}},"precision":{}}]},"ticker":{"statusCode":200,"response":{"symbol":"BTC/JPY","timestamp":1622912543000,"datetime":"2021-06-05T17:02:23.000Z","high":4158654,"low":3880000,"bid":3954841,"ask":3956969,"close":3956321,"last":3956321,"baseVolume":3412.42072353,"info":{"last":3956321,"bid":3954841,"ask":3956969,"high":4158654,"low":3880000,"volume":3412.42072353,"timestamp":1622912543}}},"tickers":{"statusCode":501,"response":""},"orderBook":{"statusCode":200,"response":{"bids":[{"price":3954841,"amount":0.02914},{"price":3954828,"amount":0.05750021},{"price":3954823,"amount":0.06},{"price":3954822,"amount":0.3387},{"price":3954268,"amount":0.0085},{"price":3954266,"amount":0.006},{"price":3954240,"amount":0.02},{"price":3954212,"amount":0.07},{"price":3954098,"amount":0.0125},{"price":3954097,"amount":0.02529604},{"price":3953901,"amount":0.01550021},{"price":3953678,"amount":0.00757725},{"price":3953612,"amount":0.0219},{"price":3953288,"amount":0.01550997},{"price":3953287,"amount":0.0155121},{"price":3953283,"amount":0.005},{"price":3953274,"amount":0.01},{"price":3953154,"amount":0.0075},{"price":3953153,"amount":0.15},{"price":3952931,"amount":0.199},{"price":3952930,"amount":0.0907},{"price":3952625,"amount":0.15},{"price":3952246,"amount":0.015},{"price":3952245,"amount":0.15},{"price":3952134,"amount":0.01550021},{"price":3952000,"amount":0.00936451},{"price":3951456,"amount":0.01548801},{"price":3951131,"amount":0.005},{"price":3951000,"amount":0.02531004},{"price":3950052,"amount":0.01550031},{"price":3950049,"amount":0.03102589},{"price":3950046,"amount":0.005},{"price":3950025,"amount":0.0251447},{"price":3950024,"amount":0.2597},{"price":3950001,"amount":0.01},{"price":3950000,"amount":1.07772151},{"price":3948897,"amount":0.2},{"price":3948030,"amount":0.015},{"price":3948020,"amount":0.005},{"price":3947752,"amount":0.01},{"price":3947597,"amount":0.01},{"price":3947277,"amount":0.02},{"price":3946072,"amount":1.26039929},{"price":3945399,"amount":0.2},{"price":3945083,"amount":0.015},{"price":3945081,"amount":0.872},{"price":3945024,"amount":0.01},{"price":3945000,"amount":0.005},{"price":3944475,"amount":0.005},{"price":3944373,"amount":0.256},{"price":3944367,"amount":6},{"price":3942971,"amount":0.2},{"price":3942222,"amount":0.05},{"price":3942000,"amount":0.01},{"price":3940001,"amount":0.015},{"price":3940000,"amount":0.055},{"price":3939855,"amount":0.2},{"price":3939453,"amount":0.3},{"price":3939264,"amount":0.02},{"price":3938945,"amount":0.04},{"price":3938770,"amount":0.005},{"price":3937848,"amount":0.00832942},{"price":3935000,"amount":0.0093},{"price":3934727,"amount":0.005},{"price":3934517,"amount":0.01264},{"price":3933491,"amount":6.9298},{"price":3932501,"amount":0.005},{"price":3932000,"amount":0.01},{"price":3930001,"amount":0.01},{"price":3930000,"amount":0.04408905},{"price":3929520,"amount":0.005},{"price":3929245,"amount":0.0593},{"price":3927730,"amount":0.02},{"price":3926608,"amount":0.01264},{"price":3925028,"amount":4.5066},{"price":3924727,"amount":0.005},{"price":3923777,"amount":0.01529138},{"price":3923000,"amount":0.02524},{"price":3922385,"amount":0.08},{"price":3922222,"amount":0.1},{"price":3922000,"amount":0.01},{"price":3921046,"amount":1.38412429},{"price":3920280,"amount":0.005},{"price":3920087,"amount":0.063942},{"price":3920001,"amount":0.0262},{"price":3920000,"amount":0.48662041},{"price":3918148,"amount":0.005},{"price":3915000,"amount":0.99},{"price":3914745,"amount":0.01264},{"price":3913000,"amount":0.005},{"price":3912000,"amount":0.01},{"price":3911030,"amount":0.005},{"price":3910001,"amount":0.015},{"price":3910000,"amount":0.34178772},{"price":3905294,"amount":0.008},{"price":3905000,"amount":0.162},{"price":3904727,"amount":0.005},{"price":3903000,"amount":0.01819},{"price":3902222,"amount":0.1},{"price":3902000,"amount":0.01},{"price":3901780,"amount":0.005},{"price":3901000,"amount":0.02563445},{"price":3900500,"amount":0.13},{"price":3900191,"amount":0.073},{"price":3900005,"amount":0.005},{"price":3900001,"amount":0.055},{"price":3900000,"amount":3.47915145},{"price":3898899,"amount":0.06412066},{"price":3895000,"amount":0.01},{"price":3892530,"amount":0.005},{"price":3892000,"amount":0.01},{"price":3890001,"amount":0.1121},{"price":3890000,"amount":0.021},{"price":3888888,"amount":0.03},{"price":3888880,"amount":0.5},{"price":3888800,"amount":0.007},{"price":3887501,"amount":0.005},{"price":3887175,"amount":0.032},{"price":3886802,"amount":0.005},{"price":3886173,"amount":0.007},{"price":3885670,"amount":0.01},{"price":3885000,"amount":0.01287001},{"price":3884075,"amount":1.8048},{"price":3883280,"amount":0.005},{"price":3882222,"amount":0.15},{"price":3882000,"amount":0.01},{"price":3881000,"amount":0.026},{"price":3880001,"amount":0.015},{"price":3880000,"amount":0.95778042},{"price":3877777,"amount":0.00515759},{"price":3877000,"amount":0.00974522},{"price":3876483,"amount":0.01},{"price":3875000,"amount":0.01},{"price":3874763,"amount":0.005},{"price":3874030,"amount":0.005},{"price":3874000,"amount":0.015},{"price":3872000,"amount":1.56},{"price":3871100,"amount":0.00774973},{"price":3870737,"amount":0.00639977},{"price":3870009,"amount":0.025},{"price":3870001,"amount":0.01},{"price":3870000,"amount":0.15242867},{"price":3867623,"amount":0.006},{"price":3867059,"amount":0.01},{"price":3867000,"amount":0.02},{"price":3866229,"amount":0.02},{"price":3866167,"amount":0.025},{"price":3865321,"amount":0.00634876},{"price":3865100,"amount":0.02},{"price":3865001,"amount":0.005},{"price":3864790,"amount":0.005},{"price":3862000,"amount":0.06178663},{"price":3861100,"amount":0.0077698},{"price":3860148,"amount":0.005},{"price":3860001,"amount":0.015},{"price":3860000,"amount":2.5342005},{"price":3858000,"amount":1},{"price":3857037,"amount":0.02592663},{"price":3856598,"amount":0.005},{"price":3856000,"amount":0.02},{"price":3855540,"amount":0.005},{"price":3855123,"amount":0.006},{"price":3855000,"amount":0.11761984},{"price":3854763,"amount":0.005},{"price":3854203,"amount":0.3},{"price":3852029,"amount":0.005},{"price":3852001,"amount":0.0389665},{"price":3852000,"amount":0.01},{"price":3851100,"amount":0.00778998},{"price":3850010,"amount":0.05},{"price":3850005,"amount":0.005},{"price":3850001,"amount":2.99837},{"price":3850000,"amount":15.87009248},{"price":3849999,"amount":0.025},{"price":3849000,"amount":0.005},{"price":3847500,"amount":0.005},{"price":3847000,"amount":0.5},{"price":3846377,"amount":0.1},{"price":3846290,"amount":0.005},{"price":3846153,"amount":0.0117},{"price":3846097,"amount":0.8627},{"price":3845195,"amount":0.01},{"price":3844735,"amount":0.01300479},{"price":3844488,"amount":0.02601126},{"price":3844203,"amount":0.5},{"price":3842623,"amount":0.006},{"price":3842501,"amount":0.005},{"price":3842000,"amount":0.01},{"price":3841550,"amount":0.005},{"price":3841500,"amount":0.35168918},{"price":3841100,"amount":0.00781026},{"price":3840001,"amount":0.015},{"price":3840000,"amount":0.59474583},{"price":3838383,"amount":0.02605262},{"price":3838000,"amount":0.005},{"price":3837040,"amount":0.505},{"price":3836757,"amount":0.03},{"price":3836589,"amount":0.005},{"price":3835000,"amount":0.16537809},{"price":3834372,"amount":0.022}],"asks":[{"price":3956969,"amount":0.1},{"price":3956970,"amount":0.06},{"price":3957251,"amount":0.07},{"price":3957397,"amount":0.22010061},{"price":3957428,"amount":0.02423},{"price":3957499,"amount":0.005},{"price":3958214,"amount":0.01550997},{"price":3958215,"amount":0.0155121},{"price":3958219,"amount":0.01550021},{"price":3958223,"amount":0.005},{"price":3958244,"amount":0.0075},{"price":3958416,"amount":0.006},{"price":3958417,"amount":0.0375},{"price":3958445,"amount":0.0168},{"price":3958589,"amount":0.1},{"price":3958789,"amount":0.15},{"price":3959318,"amount":0.01550031},{"price":3959319,"amount":0.03102589},{"price":3959324,"amount":0.3805},{"price":3959674,"amount":0.015},{"price":3959675,"amount":0.2},{"price":3959677,"amount":0.0155121},{"price":3959696,"amount":0.15},{"price":3959971,"amount":0.0907},{"price":3960329,"amount":0.122},{"price":3960343,"amount":0.13},{"price":3960635,"amount":0.15},{"price":3960763,"amount":0.2},{"price":3961000,"amount":0.5},{"price":3962499,"amount":0.005},{"price":3963495,"amount":0.015},{"price":3963558,"amount":0.1},{"price":3963720,"amount":0.2},{"price":3964038,"amount":0.2597},{"price":3964048,"amount":0.02},{"price":3964369,"amount":0.01},{"price":3964670,"amount":0.3},{"price":3966520,"amount":0.15644375},{"price":3967983,"amount":0.015},{"price":3967984,"amount":0.005},{"price":3967991,"amount":0.015},{"price":3968000,"amount":0.25197042},{"price":3968985,"amount":0.872},{"price":3969190,"amount":0.2},{"price":3969999,"amount":0.005},{"price":3970346,"amount":0.01},{"price":3970890,"amount":0.1},{"price":3971200,"amount":0.5},{"price":3971206,"amount":0.005},{"price":3972217,"amount":0.08},{"price":3972487,"amount":0.04},{"price":3972499,"amount":0.005},{"price":3972809,"amount":0.02},{"price":3974060,"amount":0.01264},{"price":3975000,"amount":0.02920418},{"price":3975185,"amount":0.005},{"price":3975770,"amount":0.005},{"price":3976705,"amount":0.02},{"price":3977002,"amount":0.021},{"price":3977499,"amount":0.005},{"price":3979846,"amount":0.2},{"price":3979999,"amount":0.02},{"price":3980000,"amount":0.12},{"price":3980652,"amount":0.01474419},{"price":3981177,"amount":0.01},{"price":3981969,"amount":0.01264},{"price":3982000,"amount":0.02},{"price":3982499,"amount":0.005},{"price":3983064,"amount":6.9612},{"price":3985010,"amount":0.005},{"price":3986784,"amount":0.005},{"price":3989474,"amount":0.08},{"price":3989999,"amount":0.005},{"price":3990000,"amount":0.14045169},{"price":3992499,"amount":0.005},{"price":3993000,"amount":0.065},{"price":3993832,"amount":0.01264},{"price":3994260,"amount":0.005},{"price":3995000,"amount":0.13675},{"price":3999995,"amount":0.005},{"price":3999999,"amount":0.11},{"price":4000000,"amount":2.72159578},{"price":4000002,"amount":0.025},{"price":4001278,"amount":0.021},{"price":4002499,"amount":0.01},{"price":4003382,"amount":0.005},{"price":4003510,"amount":0.005},{"price":4005000,"amount":0.031},{"price":4005896,"amount":0.005},{"price":4008050,"amount":4.4026},{"price":4009999,"amount":0.005},{"price":4010000,"amount":0.11507},{"price":4010666,"amount":0.0237},{"price":4012499,"amount":0.01},{"price":4012760,"amount":0.005},{"price":4013200,"amount":0.03},{"price":4015854,"amount":0.007},{"price":4019999,"amount":0.01},{"price":4020000,"amount":0.30598884},{"price":4021000,"amount":0.005005},{"price":4022000,"amount":0.005},{"price":4022010,"amount":0.005},{"price":4022499,"amount":0.005},{"price":4024153,"amount":0.005},{"price":4024999,"amount":0.005},{"price":4025000,"amount":0.005},{"price":4026000,"amount":0.01241927},{"price":4026545,"amount":0.09934074},{"price":4027000,"amount":0.01741619},{"price":4027667,"amount":0.006},{"price":4028000,"amount":0.07447864},{"price":4029999,"amount":0.005},{"price":4030000,"amount":0.035},{"price":4031260,"amount":0.005},{"price":4032499,"amount":0.005},{"price":4032780,"amount":0.005},{"price":4033655,"amount":0.00824562},{"price":4034815,"amount":0.01647182},{"price":4035000,"amount":0.005},{"price":4036879,"amount":0.005},{"price":4037982,"amount":0.005},{"price":4039999,"amount":0.01},{"price":4040000,"amount":0.15382299},{"price":4040500,"amount":0.005},{"price":4042499,"amount":0.01},{"price":4043982,"amount":0.005},{"price":4047499,"amount":0.005},{"price":4048000,"amount":0.09881422},{"price":4048888,"amount":0.1},{"price":4049750,"amount":0.005},{"price":4049982,"amount":0.005},{"price":4049995,"amount":0.005},{"price":4049999,"amount":0.005},{"price":4050000,"amount":1.14702251},{"price":4052499,"amount":0.005},{"price":4054386,"amount":1.8},{"price":4054894,"amount":0.005},{"price":4055982,"amount":0.005},{"price":4059000,"amount":0.005},{"price":4059900,"amount":0.007},{"price":4059999,"amount":0.015},{"price":4060000,"amount":0.005},{"price":4061982,"amount":0.005},{"price":4062499,"amount":0.005},{"price":4064050,"amount":0.0422625},{"price":4065000,"amount":0.09840098},{"price":4067982,"amount":0.005},{"price":4068000,"amount":0.15},{"price":4068250,"amount":0.005},{"price":4068634,"amount":0.01},{"price":4069900,"amount":0.007},{"price":4069999,"amount":0.01},{"price":4070000,"amount":0.006},{"price":4072465,"amount":0.01228716},{"price":4072499,"amount":0.005},{"price":4073982,"amount":0.005},{"price":4074919,"amount":0.12},{"price":4075000,"amount":0.449},{"price":4075093,"amount":0.8709},{"price":4077500,"amount":0.005},{"price":4079900,"amount":0.007},{"price":4079999,"amount":0.01},{"price":4082000,"amount":0.007},{"price":4082499,"amount":0.005},{"price":4083080,"amount":0.02},{"price":4084200,"amount":0.04},{"price":4084498,"amount":0.005},{"price":4085000,"amount":0.105005},{"price":4085433,"amount":0.025},{"price":4085670,"amount":0.015},{"price":4086750,"amount":0.005},{"price":4086993,"amount":0.1},{"price":4088650,"amount":0.005},{"price":4089900,"amount":0.007},{"price":4089999,"amount":0.005},{"price":4090000,"amount":0.08531645},{"price":4090020,"amount":0.1},{"price":4091692,"amount":0.005},{"price":4092499,"amount":0.01},{"price":4093982,"amount":0.005},{"price":4094219,"amount":0.1},{"price":4095000,"amount":0.005002},{"price":4095856,"amount":0.014},{"price":4095990,"amount":0.005},{"price":4097000,"amount":0.005},{"price":4097287,"amount":0.02440639},{"price":4098000,"amount":0.02495757},{"price":4098111,"amount":0.15219798},{"price":4098634,"amount":0.01},{"price":4099900,"amount":0.007},{"price":4099995,"amount":0.005},{"price":4099999,"amount":0.025},{"price":4100000,"amount":1.60193868},{"price":4101015,"amount":0.025},{"price":4102499,"amount":0.01},{"price":4102500,"amount":0.05},{"price":4103982,"amount":0.005},{"price":4105240,"amount":0.005},{"price":4108050,"amount":0.04181422},{"price":4109001,"amount":0.03}]}},"trades":{"statusCode":200,"response":[{"id":"186796054","info":{"id":186796054,"amount":"0.04449647","rate":3956062,"pair":"btc_jpy","order_type":"sell","created_at":"2021-06-05T17:01:17.000Z"},"timestamp":1622912477000,"datetime":"2021-06-05T17:01:17.000Z","symbol":"BTC/JPY","side":"sell","price":3956062,"amount":0.04449647},{"id":"186796055","info":{"id":186796055,"amount":"0.0104","rate":3954585,"pair":"btc_jpy","order_type":"sell","created_at":"2021-06-05T17:01:20.000Z"},"timestamp":1622912480000,"datetime":"2021-06-05T17:01:20.000Z","symbol":"BTC/JPY","side":"sell","price":3954585,"amount":0.0104},{"id":"186796056","info":{"id":186796056,"amount":"0.005","rate":3956245,"pair":"btc_jpy","order_type":"buy","created_at":"2021-06-05T17:01:22.000Z"},"timestamp":1622912482000,"datetime":"2021-06-05T17:01:22.000Z","symbol":"BTC/JPY","side":"buy","price":3956245,"amount":0.005},{"id":"186796057","info":{"id":186796057,"amount":"0.01550021","rate":3956705,"pair":"btc_jpy","order_type":"buy","created_at":"2021-06-05T17:01:24.000Z"},"timestamp":1622912484000,"datetime":"2021-06-05T17:01:24.000Z","symbol":"BTC/JPY","side":"buy","price":3956705,"amount":0.01550021},{"id":"186796059","info":{"id":186796059,"amount":"0.021","rate":3956461,"pair":"btc_jpy","order_type":"buy","created_at":"2021-06-05T17:01:53.000Z"},"timestamp":1622912513000,"datetime":"2021-06-05T17:01:53.000Z","symbol":"BTC/JPY","side":"buy","price":3956461,"amount":0.021},{"id":"186796058","info":{"id":186796058,"amount":"0.005","rate":3956451,"pair":"btc_jpy","order_type":"buy","created_at":"2021-06-05T17:01:53.000Z"},"timestamp":1622912513000,"datetime":"2021-06-05T17:01:53.000Z","symbol":"BTC/JPY","side":"buy","price":3956451,"amount":0.005},{"id":"186796061","info":{"id":186796061,"amount":"0.01","rate":3957346,"pair":"btc_jpy","order_type":"buy","created_at":"2021-06-05T17:01:56.000Z"},"timestamp":1622912516000,"datetime":"2021-06-05T17:01:56.000Z","symbol":"BTC/JPY","side":"buy","price":3957346,"amount":0.01},{"id":"186796060","info":{"id":186796060,"amount":"0.00008178","rate":3957188,"pair":"btc_jpy","order_type":"buy","created_at":"2021-06-05T17:01:56.000Z"},"timestamp":1622912516000,"datetime":"2021-06-05T17:01:56.000Z","symbol":"BTC/JPY","side":"buy","price":3957188,"amount":0.00008178},{"id":"186796063","info":{"id":186796063,"amount":"0.0925","rate":3956321,"pair":"btc_jpy","order_type":"buy","created_at":"2021-06-05T17:02:09.000Z"},"timestamp":1622912529000,"datetime":"2021-06-05T17:02:09.000Z","symbol":"BTC/JPY","side":"buy","price":3956321,"amount":0.0925},{"id":"186796062","info":{"id":186796062,"amount":"0.0075","rate":3956552,"pair":"btc_jpy","order_type":"sell","created_at":"2021-06-05T17:02:09.000Z"},"timestamp":1622912529000,"datetime":"2021-06-05T17:02:09.000Z","symbol":"BTC/JPY","side":"sell","price":3956552,"amount":0.0075}]}}